iemtools/__init__.py
iemtools/morris.py
iemtools/motion.py
iemtools/nor.py
iemtools/simulations.py
iemtools/ymaze.py
iemtools-0.3.1.dist-info/LICENSE
iemtools-0.3.1.dist-info/METADATA
iemtools-0.3.1.dist-info/WHEEL
iemtools-0.3.1.dist-info/top_level.txt
iemtools-0.3.1.dist-info/RECORD
