Metadata-Version: 2.1
Name: iemtools
Version: 0.3.1
Summary: Behavioural tests analysis tool
Author-email: Sely Papan <sely.papan@iem.cas.cz>
Project-URL: Homepage, https://github.com/selypapan/iem_cas_projects/blob/main/iemtools_package/
Project-URL: Issues, https://github.com/selypapan/iem_cas_projects/issues
Classifier: Programming Language :: Python :: 3
Classifier: Operating System :: OS Independent
Requires-Python: >=3.12.4
License-File: LICENSE
